printwatch/__init__.py
printwatch/app.py
printwatch/redirection.py
printwatch/utils.py
printwatch/static/home.css
printwatch/templates/home.html
printwatch/templates/logs.html
printwatch-0.0.7a0.dist-info/METADATA
printwatch-0.0.7a0.dist-info/WHEEL
printwatch-0.0.7a0.dist-info/licenses/LICENSE
printwatch-0.0.7a0.dist-info/RECORD
