Metadata-Version: 2.1
Name: printwatch
Version: 0.0.7a0
Summary: Tired of running long tasks? Try Printwatch to monitor it from local network!
Project-URL: Homepage, https://github.com/ashwin2k/printwatch
Project-URL: Bug Tracker, https://github.com/ashwin2k/printwatch/issues
Author-email: Ashwin Kumar Udayakumar <ashwin102000@gmail.com>
License-File: LICENSE
Classifier: License :: OSI Approved :: MIT License
Classifier: Operating System :: OS Independent
Classifier: Programming Language :: Python :: 3
Requires-Python: >=3.7
